Workbook

Sheet Prices
A1: Strip Month | B1: Jet Fuel Price | C1: Log return | D1: 3-strip volatility
A2: 2025-04 | B2: 2.31
A3: 2025-05 | B3: 2.28 | C3: =LN(B3/B2)*100
A4: 2025-06 | B4: 2.34 | C4: =LN(B4/B3)*100
A5: 2025-07 | B5: 2.41 | C5: =LN(B5/B4)*100 | D5: =STDEV.S(C3:C5)
A6: 2025-08 | B6: 2.39 | C6: =LN(B6/B5)*100 | D6: =STDEV.S(C4:C6)
A7: 2025-09 | B7: 2.44 | C7: =LN(B7/B6)*100 | D7: =STDEV.S(C5:C7)
A8: 2025-10 | B8: 2.49 | C8: =LN(B8/B7)*100 | D8: =STDEV.S(C6:C8)
A9: 2025-11 | B9: 2.52 | C9: =LN(B9/B8)*100 | D9: =STDEV.S(C7:C9)

Sheet Hedges
A1: Desk | B1: Forecast Gallons | C1: Hedge Ratio | D1: Hedged Gallons | E1: Notional Cost | F1: Margin Buffer
A2: Domestic | B2: 1200000 | C2: 0.55 | D2: =B2*C2 | E2: =D2*Summary!$B$2 | F2: =E2*Summary!$B$4/100*1.65
A3: Atlantic | B3: 800000 | C3: 0.7 | D3: =B3*C3 | E3: =D3*Summary!$B$2 | F3: =E3*Summary!$B$4/100*1.65
A4: Cargo | B4: 650000 | C4: 0.4 | D4: =B4*C4 | E4: =D4*Summary!$B$2 | F4: =E4*Summary!$B$4/100*1.65

Sheet Summary
A1: Metric | B1: Value
A2: Average strip price | B2: =AVERAGE(Prices!B2:B9)
A3: Latest 3-strip volatility | B3: =Prices!D9
A4: Annualized volatility | B4: =B3*SQRT(12)
A5: Total hedged gallons | B5: =SUM(Hedges!D2:D4)
A6: Total notional cost | B6: =SUM(Hedges!E2:E4)
A7: Total margin buffer | B7: =SUM(Hedges!F2:F4)
A8: Largest desk | B8: =INDEX(Hedges!A2:A4,MATCH(MAX(Hedges!E2:E4),Hedges!E2:E4,0))
