Workbook

Sheet Sessions
A1: Session | B1: Forecast attendees | C1: Hours | D1: Premium share
A2: Keynote | B2: 420 | C2: 2.5 | D2: 0.18
A3: Breakout A | B3: 160 | C3: 1.5 | D3: 0.1
A4: Breakout B | B4: 190 | C4: 1.5 | D4: 0.12
A5: Expo Floor | B5: 510 | C5: 4 | D5: 0.22
A6: Closing Panel | B6: 360 | C6: 2 | D6: 0.15

Sheet Rates
A1: Parameter | B1: Value
A2: Ushers per 120 attendees | B2: 1
A3: Registration per 180 attendees | B3: 1
A4: Support per 250 attendees | B4: 1
A5: Supervisor ratio | B5: 0.15
A6: Usher wage | B6: 22
A7: Registration wage | B7: 24
A8: Support wage | B8: 26
A9: Supervisor wage | B9: 35
A10: Premium multiplier | B10: 1.15
A11: Surge multiplier | B11: 1.3
A12: Sponsorship revenue | B12: 185000
A13: Ticket price | B13: 145

Sheet Staffing_Model
A1: Session | B1: Attendees | C1: Ushers | D1: Registration | E1: Support | F1: Supervisors | G1: Labor hours | H1: Labor cost | I1: Premium attendees
A2: =Sessions!A2 | B2: =Sessions!B2 | C2: =ROUNDUP(B2/120*Rates!$B$2,0) | D2: =ROUNDUP(B2/180*Rates!$B$3,0) | E2: =ROUNDUP(B2/250*Rates!$B$4,0) | F2: =ROUNDUP((C2+D2+E2)*Rates!$B$5,0) | G2: =(C2+D2+E2+F2)*Sessions!C2 | H2: =Sessions!C2*(C2*Rates!$B$6+D2*Rates!$B$7+E2*Rates!$B$8+F2*Rates!$B$9) | I2: =B2*Sessions!D2
A3: =Sessions!A3 | B3: =Sessions!B3 | C3: =ROUNDUP(B3/120*Rates!$B$2,0) | D3: =ROUNDUP(B3/180*Rates!$B$3,0) | E3: =ROUNDUP(B3/250*Rates!$B$4,0) | F3: =ROUNDUP((C3+D3+E3)*Rates!$B$5,0) | G3: =(C3+D3+E3+F3)*Sessions!C3 | H3: =Sessions!C3*(C3*Rates!$B$6+D3*Rates!$B$7+E3*Rates!$B$8+F3*Rates!$B$9) | I3: =B3*Sessions!D3
A4: =Sessions!A4 | B4: =Sessions!B4 | C4: =ROUNDUP(B4/120*Rates!$B$2,0) | D4: =ROUNDUP(B4/180*Rates!$B$3,0) | E4: =ROUNDUP(B4/250*Rates!$B$4,0) | F4: =ROUNDUP((C4+D4+E4)*Rates!$B$5,0) | G4: =(C4+D4+E4+F4)*Sessions!C4 | H4: =Sessions!C4*(C4*Rates!$B$6+D4*Rates!$B$7+E4*Rates!$B$8+F4*Rates!$B$9) | I4: =B4*Sessions!D4
A5: =Sessions!A5 | B5: =Sessions!B5 | C5: =ROUNDUP(B5/120*Rates!$B$2,0) | D5: =ROUNDUP(B5/180*Rates!$B$3,0) | E5: =ROUNDUP(B5/250*Rates!$B$4,0) | F5: =ROUNDUP((C5+D5+E5)*Rates!$B$5,0) | G5: =(C5+D5+E5+F5)*Sessions!C5 | H5: =Sessions!C5*(C5*Rates!$B$6+D5*Rates!$B$7+E5*Rates!$B$8+F5*Rates!$B$9) | I5: =B5*Sessions!D5
A6: =Sessions!A6 | B6: =Sessions!B6 | C6: =ROUNDUP(B6/120*Rates!$B$2,0) | D6: =ROUNDUP(B6/180*Rates!$B$3,0) | E6: =ROUNDUP(B6/250*Rates!$B$4,0) | F6: =ROUNDUP((C6+D6+E6)*Rates!$B$5,0) | G6: =(C6+D6+E6+F6)*Sessions!C6 | H6: =Sessions!C6*(C6*Rates!$B$6+D6*Rates!$B$7+E6*Rates!$B$8+F6*Rates!$B$9) | I6: =B6*Sessions!D6

Sheet Scenario_Compare
A1: Scenario | B1: Total attendees | C1: Total labor hours | D1: Total labor cost | E1: Revenue | F1: Margin
A2: Standard | B2: =SUM(Staffing_Model!B2:B6)*1 | C2: =SUM(Staffing_Model!G2:G6)*1 | D2: =SUM(Staffing_Model!H2:H6)*1 | E2: =Rates!$B$12 + B2*Rates!$B$13 | F2: =E2-D2
A3: Premium | B3: =SUM(Staffing_Model!B2:B6)*Rates!$B$10 | C3: =SUM(Staffing_Model!G2:G6)*Rates!$B$10 | D3: =SUM(Staffing_Model!H2:H6)*Rates!$B$10 | E3: =Rates!$B$12 + B3*Rates!$B$13 | F3: =E3-D3
A4: Surge | B4: =SUM(Staffing_Model!B2:B6)*Rates!$B$11 | C4: =SUM(Staffing_Model!G2:G6)*Rates!$B$11 | D4: =SUM(Staffing_Model!H2:H6)*Rates!$B$11 | E4: =Rates!$B$12 + B4*Rates!$B$13 | F4: =E4-D4

Sheet Summary
A1: Metric | B1: Value
A2: Most expensive session | B2: =INDEX(Staffing_Model!A2:A6,MATCH(MAX(Staffing_Model!H2:H6),Staffing_Model!H2:H6,0))
A3: Standard margin | B3: =Scenario_Compare!F2
A4: Surge margin | B4: =Scenario_Compare!F4
A5: Total premium attendees | B5: =SUM(Staffing_Model!I2:I6)
